latextable_lite/__init__.py
latextable_lite/latextable_lite.py
latextable_lite-0.0.2.dist-info/LICENSE
latextable_lite-0.0.2.dist-info/METADATA
latextable_lite-0.0.2.dist-info/WHEEL
latextable_lite-0.0.2.dist-info/top_level.txt
latextable_lite-0.0.2.dist-info/RECORD
