Metadata-Version: 2.1
Name: latextable-lite
Version: 0.0.2
Summary: Create simple Latex tables
Home-page: https://github.com/huisyy/latextable-lite
Author: Megan Hu
Author-email: meganhu@berkeley.edu
Classifier: Programming Language :: Python :: 3
Classifier: License :: OSI Approved :: MIT License
Classifier: Operating System :: OS Independent
Requires-Python: >=3.6
License-File: LICENSE
